pycountwords/__init__.py
pycountwords/plotting.py
pycountwords/pycountwords.py
pycountwords/zen.txt
pycountwords-0.1.0.dist-info/LICENSE
pycountwords-0.1.0.dist-info/METADATA
pycountwords-0.1.0.dist-info/WHEEL
pycountwords-0.1.0.dist-info/RECORD
